odoo/addons/purchase_order_line_deep_sort/README.rst
odoo/addons/purchase_order_line_deep_sort/__init__.py
odoo/addons/purchase_order_line_deep_sort/__manifest__.py
odoo/addons/purchase_order_line_deep_sort/i18n/es.po
odoo/addons/purchase_order_line_deep_sort/i18n/purchase_order_line_deep_sort.pot
odoo/addons/purchase_order_line_deep_sort/models/__init__.py
odoo/addons/purchase_order_line_deep_sort/models/purchase_order.py
odoo/addons/purchase_order_line_deep_sort/models/res_company.py
odoo/addons/purchase_order_line_deep_sort/models/res_config_settings.py
odoo/addons/purchase_order_line_deep_sort/readme/CONFIGURE.rst
odoo/addons/purchase_order_line_deep_sort/readme/CONTRIBUTORS.rst
odoo/addons/purchase_order_line_deep_sort/readme/DESCRIPTION.rst
odoo/addons/purchase_order_line_deep_sort/readme/ROADMAP.rst
odoo/addons/purchase_order_line_deep_sort/readme/USAGE.rst
odoo/addons/purchase_order_line_deep_sort/static/description/icon.png
odoo/addons/purchase_order_line_deep_sort/static/description/index.html
odoo/addons/purchase_order_line_deep_sort/tests/__init__.py
odoo/addons/purchase_order_line_deep_sort/tests/test_purchase_order_line_deep_sort.py
odoo/addons/purchase_order_line_deep_sort/views/purchase_order_views.xml
odoo/addons/purchase_order_line_deep_sort/views/res_config_settings_views.xml
odoo11_addon_purchase_order_line_deep_sort-11.0.1.0.0.99.dev11.dist-info/METADATA
odoo11_addon_purchase_order_line_deep_sort-11.0.1.0.0.99.dev11.dist-info/WHEEL
odoo11_addon_purchase_order_line_deep_sort-11.0.1.0.0.99.dev11.dist-info/top_level.txt
odoo11_addon_purchase_order_line_deep_sort-11.0.1.0.0.99.dev11.dist-info/RECORD
